indo_python/__init__.py
indo_python/indo_python.py
indo_python-0.1.0.dist-info/METADATA
indo_python-0.1.0.dist-info/WHEEL
indo_python-0.1.0.dist-info/top_level.txt
indo_python-0.1.0.dist-info/RECORD
